{
  "$schema": "https://json-schema.org/draft/2020-12/schema",
  "$id": "https://raw.githubusercontent.com/krisarmstrong/stem/main/docs/schemas/api/auth-refresh.schema.json",
  "$ref": "#/$defs/AuthRefreshRequest",
  "$defs": {
    "AuthRefreshRequest": {
      "properties": {
        "refreshToken": {
          "type": "string"
        }
      },
      "additionalProperties": false,
      "type": "object",
      "required": [
        "refreshToken"
      ]
    }
  },
  "title": "AuthRefreshRequest",
  "description": "AuthRefreshRequest — generated from the Go struct in internal/api; refresh with `make schema` after struct changes."
}
